AUTHORS.rst
CONTRIBUTORS.md
LICENSE
MANIFEST.in
README.md
requirements.txt
setup.py
tox.ini
climetlab_wekeo_ecmwf/__init__.py
climetlab_wekeo_ecmwf/cams_europe_air_quality_forecasts.py
climetlab_wekeo_ecmwf/cams_europe_air_quality_reanalyses.py
climetlab_wekeo_ecmwf/cams_global_atmospheric_composition_forecasts.py
climetlab_wekeo_ecmwf/cams_global_emission_inventories.py
climetlab_wekeo_ecmwf/cams_global_fire_emissions_gfas.py
climetlab_wekeo_ecmwf/cams_global_ghg_reanalysis_egg4.py
climetlab_wekeo_ecmwf/cams_global_ghg_reanalysis_egg4_monthly.py
climetlab_wekeo_ecmwf/cams_global_greenhouse_gas_inversion.py
climetlab_wekeo_ecmwf/cams_global_radiative_forcing_auxilliary_variables.py
climetlab_wekeo_ecmwf/cams_global_radiative_forcings.py
climetlab_wekeo_ecmwf/cams_global_reanalysis_eac4.py
climetlab_wekeo_ecmwf/cams_global_reanalysis_eac4_monthly.py
climetlab_wekeo_ecmwf/cams_solar_radiation_timeseries.py
climetlab_wekeo_ecmwf/cems_fire_historical_v1.py
climetlab_wekeo_ecmwf/derived_near_surface_meteorological_variables.py
climetlab_wekeo_ecmwf/derived_reanalysis_energy_moisture_budget.py
climetlab_wekeo_ecmwf/derived_utci_historical.py
climetlab_wekeo_ecmwf/ecv_for_climate_change.py
climetlab_wekeo_ecmwf/efas_forecast.py
climetlab_wekeo_ecmwf/efas_historical.py
climetlab_wekeo_ecmwf/efas_reforecast.py
climetlab_wekeo_ecmwf/efas_seasonal.py
climetlab_wekeo_ecmwf/efas_seasonal_reforecast.py
climetlab_wekeo_ecmwf/insitu_glaciers_elevation_mass.py
climetlab_wekeo_ecmwf/insitu_glaciers_extent.py
climetlab_wekeo_ecmwf/insitu_gridded_observations_alpine_precipitation.py
climetlab_wekeo_ecmwf/insitu_gridded_observations_europe.py
climetlab_wekeo_ecmwf/insitu_gridded_observations_global_and_regional.py
climetlab_wekeo_ecmwf/insitu_gridded_observations_nordic.py
climetlab_wekeo_ecmwf/insitu_observations_gnss.py
climetlab_wekeo_ecmwf/insitu_observations_gruan_reference_network.py
climetlab_wekeo_ecmwf/insitu_observations_igra_baseline_network.py
climetlab_wekeo_ecmwf.egg-info/PKG-INFO
climetlab_wekeo_ecmwf.egg-info/SOURCES.txt
climetlab_wekeo_ecmwf.egg-info/dependency_links.txt
climetlab_wekeo_ecmwf.egg-info/entry_points.txt
climetlab_wekeo_ecmwf.egg-info/requires.txt
climetlab_wekeo_ecmwf.egg-info/top_level.txt
climetlab_wekeo_ecmwf.egg-info/zip-safe
